khadoop/__init__.py
khadoop/hiveserver/__init__.py
khadoop/hiveserver/logserver.py
khadoop/yarn/__init__.py
khadoop/yarn/config.py
khadoop/yarn/logmr.py
khadoop/yarn/logrm.py
khadoop/yarn/timeserver.py
khadoop-1.4.0.dist-info/WHEEL
khadoop-1.4.0.dist-info/METADATA
khadoop-1.4.0.dist-info/RECORD
