Metadata-Version: 2.1
Name: khadoop
Version: 1.4.0
Summary: 
Author: Khalid
Author-email: khalidck@gmail.com
Requires-Python: >=3.8,<4.0
Classifier: Programming Language :: Python :: 3
Classifier: Programming Language :: Python :: 3.8
Classifier: Programming Language :: Python :: 3.9
Requires-Dist: arrow (>=0.17.0,<0.18.0)
Requires-Dist: humanize (>=3.2.0,<4.0.0)
Requires-Dist: loguru (>=0.5.3,<0.6.0)
Requires-Dist: pandas (>=1.1,<2.0)
Requires-Dist: pydantic (>=1.7.3,<2.0.0)
Requires-Dist: stringcase (>=1.2.0,<2.0.0)
Requires-Dist: toolz (>=0.11.1,<0.12.0)
